pyab_experiment/__init__.py
pyab_experiment/binning/__init__.py
pyab_experiment/binning/binning.py
pyab_experiment/codegen/__init__.py
pyab_experiment/codegen/python/__init__.py
pyab_experiment/codegen/python/custom_exceptions.py
pyab_experiment/codegen/python/python_generator.py
pyab_experiment/data_structures/__init__.py
pyab_experiment/data_structures/syntax_tree.py
pyab_experiment/experiment_evaluator.py
pyab_experiment/language/README.rst
pyab_experiment/language/__init__.py
pyab_experiment/language/grammar.py
pyab_experiment/language/lexer.py
pyab_experiment/sly/README.md
pyab_experiment/sly/__init__.py
pyab_experiment/sly/ast.py
pyab_experiment/sly/docparse.py
pyab_experiment/sly/lex.py
pyab_experiment/sly/yacc.py
pyab_experiment/utils/__init__.py
pyab_experiment/utils/custom_operators.py
pyab_experiment/utils/stats.py
pyab_experiment/utils/wraper_functions.py
py_ab_experiment-0.3.2.dist-info/LICENSE
py_ab_experiment-0.3.2.dist-info/METADATA
py_ab_experiment-0.3.2.dist-info/WHEEL
py_ab_experiment-0.3.2.dist-info/RECORD
