Metadata-Version: 2.1
Name: py-ab-experiment
Version: 0.3.2
Summary: Pythonic AB Experiment Framework
Home-page: https://github.com/gus-fr/py_ab
License: GPL-3.0-or-later
Author: gus-fr
Author-email: gustavo_frigo@hotmail.com
Requires-Python: >=3.10,<4.0
Classifier: License :: OSI Approved :: GNU General Public License v3 or later (GPLv3+)
Classifier: Programming Language :: Python :: 3
Classifier: Programming Language :: Python :: 3.10
Classifier: Programming Language :: Python :: 3.11
Classifier: Programming Language :: Python :: 3.12
Classifier: Programming Language :: Python :: 3.13
Requires-Dist: black (>=24.2.0,<25.0.0)
Requires-Dist: pydantic (>=1.10.0,<2.0.0)
Project-URL: Repository, https://github.com/gus-fr/py_ab
